{
  "participante": "victorverdoodt-cs",
  "descricao": "'total_liquido' é sua pontuação final. Equivale ao seu lucro. Fórmula: total_liquido + (total_liquido * p99.bonus) - (total_liquido * multa.porcentagem)",
  "total_liquido": 201911.4695,
  "total_bruto": 332807.60000000003,
  "total_taxas": 22174.57,
  "p99": {
    "valor": "68.61897453000002ms",
    "bonus": 0,
    "max_requests": "550",
    "descricao": "Fórmula para o bônus: max((11 - p99.valor) * 0.02, 0)"
  },
  "multa": {
    "porcentagem": 0.35,
    "total": 108721.5605,
    "composicao": {
      "descricao": "Se 'total_bruto' != 'total_bruto_esperado' ou 'total_inconsistencias' > 0, há multa de 35%.",
      "total_bruto_esperado": 332807.6,
      "total_inconsistencias": 417.8999999999978
    }
  },
  "pagamentos": {
    "qtd_sucesso": 16724,
    "qtd_falha": 0
  },
  "default": {
    "total_bruto": 277465.7,
    "num_pagamentos": 13943,
    "total_taxas": 13873.285000000002
  },
  "fallback": {
    "total_bruto": 55341.9,
    "num_pagamentos": 2781,
    "total_taxas": 8301.285
  }
}