{
  "participante": "davidalecrim1-go-1",
  "descricao": "'total_liquido' é sua pontuação final. Equivale ao seu lucro. Fórmula: total_liquido + (total_liquido * p99.bonus) - (total_liquido * multa.porcentagem)",
  "total_liquido": 206746.06292237,
  "total_bruto": 303057.09999995644,
  "total_taxas": 31558.41499999528,
  "p99": {
    "valor": "5.42503419999998ms",
    "bonus": 0.1114993160000004,
    "max_requests": "500",
    "descricao": "Fórmula para o bônus: max((11 - p99.valor) * 0.02, 0)"
  },
  "multa": {
    "porcentagem": 0.35,
    "total": 95024.5397499864,
    "composicao": {
      "descricao": "Se 'total_bruto' != 'total_bruto_esperado' ou 'total_inconsistencias' > 0, há multa de 35%.",
      "total_bruto_esperado": 303057.1,
      "total_inconsistencias": 19.900000010669828
    }
  },
  "pagamentos": {
    "qtd_sucesso": 15229,
    "qtd_falha": 0
  },
  "default": {
    "total_bruto": 139001.4999999819,
    "num_pagamentos": 6985,
    "total_taxas": 6950.074999999095
  },
  "fallback": {
    "total_bruto": 164055.59999997457,
    "num_pagamentos": 8244,
    "total_taxas": 24608.339999996184
  }
}