{
  "participante": "alvesluc-node",
  "total_liquido": 166342.10999999195,
  "total_bruto": 182522.79999999172,
  "total_taxas": 16180.689999999779,
  "descricao": "'total_liquido' é sua pontuação final. Equivale ao seu lucro. Fórmula: total_liquido + (total_liquido * p99.bonus) - (total_liquido * multa.porcentagem)",
  "p99": {
    "valor": "158.39ms",
    "bonus": "0%",
    "max_requests": "550",
    "descricao": "Fórmula para o bônus: max((11 - p99.valor) * 0.02, 0)"
  },
  "multa": {
    "porcentagem": 0,
    "total": 0,
    "composicao": {
      "num_inconsistencias": 0,
      "descricao": "Se 'num_inconsistencias' > 0, há multa de 35%."
    }
  },
  "caixa_dois": {
    "detectado": false,
    "descricao": "Se 'lag' for negativo, significa que seu backend registrou mais pagamentos do que solicitado, automaticamente desclassificando sua submissão!"
  },
  "lag": {
    "num_pagamentos_total": 9172,
    "num_pagamentos_solicitados": 16538,
    "lag": 7366,
    "descricao": "Lag é a diferença entre a quantidade de solicitações de pagamentos e o que foi realmente computado pelo backend. Mostra a perda de pagamentos possivelmente por estarem enfileirados."
  },
  "pagamentos_solicitados": {
    "qtd_sucesso": 16538,
    "qtd_falha": 0,
    "descricao": "'qtd_sucesso' foram requests bem sucedidos para 'POST /payments' e 'qtd_falha' os requests com erro."
  },
  "pagamentos_realizados_default": {
    "total_bruto": 111977.2999999898,
    "num_pagamentos": 5627,
    "total_taxas": 5598.86499999949,
    "descricao": "Informações do backend sobre solicitações de pagamento para o Payment Processor Default."
  },
  "pagamentos_realizados_fallback": {
    "total_bruto": 70545.50000000192,
    "num_pagamentos": 3545,
    "total_taxas": 10581.825000000288,
    "descricao": "Informações do backend sobre solicitações de pagamento para o Payment Processor Fallback."
  }
}