{
  "participante": "maxsonferovante",
  "total_liquido": 146705.53625,
  "total_bruto": 242561.09999999998,
  "total_taxas": 16860.274999999998,
  "descricao": "'total_liquido' é sua pontuação final. Equivale ao seu lucro. Fórmula: total_liquido + (total_liquido * p99.bonus) - (total_liquido * multa.porcentagem)",
  "p99": {
    "valor": "39.256014100000044ms",
    "bonus": 0,
    "max_requests": "550",
    "descricao": "Fórmula para o bônus: max((11 - p99.valor) * 0.02, 0)"
  },
  "multa": {
    "porcentagem": 0.35,
    "total": 78995.28874999999,
    "composicao": {
      "total_inconsistencias": 139.30000000000143,
      "descricao": "Se 'total_inconsistencias' > 0, há multa de 35%."
    }
  },
  "lag": {
    "num_pagamentos_total": 12189,
    "num_pagamentos_solicitados": 16704,
    "lag": 4515,
    "descricao": "Lag é a diferença entre a quantidade de solicitações de pagamentos vs o que foi realmente computado pelo backend. Mostra a perda de pagamentos possivelmente por estarem enfileirados."
  },
  "pagamentos_solicitados": {
    "qtd_sucesso": 16704,
    "qtd_falha": 0,
    "descricao": "'qtd_sucesso' foram requests bem sucedidos para 'POST /payments' e 'qtd_falha' os requests com erro."
  },
  "pagamentos_realizados_default": {
    "total_bruto": 195238.9,
    "num_pagamentos": 9811,
    "total_taxas": 9761.945,
    "descricao": "Informações do backend sobre solicitações de pagamento para o Payment Processor Default."
  },
  "pagamentos_realizados_fallback": {
    "total_bruto": 47322.2,
    "num_pagamentos": 2378,
    "total_taxas": 7098.329999999999,
    "descricao": "Informações do backend sobre solicitações de pagamento para o Payment Processor Fallback."
  }
}